{"id":"5ac2lB","name":"Main Brewery","streetAddress":"11616 E. Montgomery Dr.","locality":"Spokane Valley","region":"Washington","postalCode":"99206","website":"http://www.12stringbrewingco.com/","hoursOfOperation":"Tue - Thu: 3:00 pm - 10:00 pm\r\nFri: 3:00 pm - 11:00 pm\r\nSat: 12:00 pm - 11:00 pm","isPrimary":"Y","inPlanning":"N","isClosed":"N","openToPublic":"Y","locationType":"micro","locationTypeDisplay":"Micro Brewery","countryIsoCode":"US","status":"verified","statusDisplay":"Verified","breweryId":"fWfbGJ","createDate":[2012,1,3,2,41,43],"updateDate":[2015,11,16,21,9,8],"latitude":47.6771034,"longitude":-117.2487522,"brewery":{"id":"fWfbGJ","name":"Twelve String Brewing Company","description":"Located in Spokane Valley, WA, 12 String Brewing Company marries the brewer’s love of music, especially the 12 string guitar, with his passion for brewing spectacular beer. Our goal is to craft a variety of great beer in the Northwest tradition. We will also feature several other beers from our brewing friends.\r\n\r\nYes, 12 string brewing company crafts great beer in the Northwest tradition. This is an example of a small scale brewing company at its best! The brewery includes an onsite tap room with plenty of seating and from time to time, great live music.  And when not brewing one of his great beers, you just may just find the brewer hanging out, playing his 12 string guitar.","website":"http://www.12stringbrewingco.com/","established":"2011","isOrganic":"N","status":"verified","statusDisplay":"Verified","createDate":[2012,1,3,2,41,43],"updateDate":[2015,12,22,15,14,50]},"country":{"isoCode":"US","name":"UNITED STATES","displayName":"United States","isoThree":"USA","numberCode":840,"createDate":[2012,1,3,2,41,33]}}