{"id":"hgjj29","name":"Main Brewery","streetAddress":"22329 53rd Avenue SE","locality":"Bothell","region":"Washington","postalCode":"98021","phone":"206-553-9223","website":"http://www.foggynogginbrewing.com/","hoursOfOperation":"Most Saturdays 1-4pm","isPrimary":"Y","inPlanning":"N","isClosed":"N","openToPublic":"Y","locationType":"micro","locationTypeDisplay":"Micro Brewery","countryIsoCode":"US","status":"verified","statusDisplay":"Verified","breweryId":"HlrMmv","createDate":[2012,1,3,2,41,55],"updateDate":[2014,7,23,19,11,34],"latitude":47.794472,"longitude":-122.160868,"brewery":{"id":"HlrMmv","name":"Foggy Noggin Brewing","description":"We are brewers of great English Styled Ales on a very small 1/2 BBL system. We are one of the world’s smallest production breweries. We take great pride in every batch to bring you consistent high quality brews year-round. You are able to get our fresh beers at our tasting room, located at our brewery in Bothell, WA and at several accounts that rotate our beers thru their line-up.","website":"http://www.foggynogginbrewing.com/","established":"2010","isOrganic":"N","status":"verified","statusDisplay":"Verified","createDate":[2012,1,3,2,41,55],"updateDate":[2015,12,22,15,19,16],"images":{"icon":"https://s3.amazonaws.com/brewerydbapi/brewery/HlrMmv/upload_GQZRZn-icon.png","medium":"https://s3.amazonaws.com/brewerydbapi/brewery/HlrMmv/upload_GQZRZn-medium.png","large":"https://s3.amazonaws.com/brewerydbapi/brewery/HlrMmv/upload_GQZRZn-large.png"}},"country":{"isoCode":"US","name":"UNITED STATES","displayName":"United States","isoThree":"USA","numberCode":840,"createDate":[2012,1,3,2,41,33]}}