{"id":"rfXHD7","name":"Main Brewery","streetAddress":"1550 NW 49th Street","locality":"Seattle","region":"Washington","postalCode":"98107","phone":"206-465-0078","website":"http://hilliardsbeer.com/","hoursOfOperation":"Monday-Friday 9 am until 5 pm","isPrimary":"Y","inPlanning":"N","isClosed":"N","openToPublic":"Y","locationType":"micro","locationTypeDisplay":"Micro Brewery","countryIsoCode":"US","status":"verified","statusDisplay":"Verified","breweryId":"o4FfAx","createDate":[2012,1,3,2,41,57],"updateDate":[2014,7,23,19,11,34],"latitude":47.6644943,"longitude":-122.3779255,"brewery":{"id":"o4FfAx","name":"Hilliard's Beer","description":"We opened our doors in October, 2011 with focus on beer in cans.  Founded by Ryan Hilliard and Adam Merkl, we now have a much larger crew and even more beer.\r\n\r\nWe self-distribute canned and draft beer to bars and restaurants within Seattle and have a 1 case minimum.  Please contact Adam Merkl at 206-915-3303 or adam@hilliardsbeer.com for info.  Off-premise sales within Seattle as well as on and off-premise sales of our canned beer outside Seattle is handled by our distributor, Noble.","website":"http://www.hilliardsbeer.com","established":"2011","isOrganic":"N","status":"verified","statusDisplay":"Verified","createDate":[2012,1,3,2,41,57],"updateDate":[2015,12,22,15,15,30],"images":{"icon":"https://s3.amazonaws.com/brewerydbapi/brewery/o4FfAx/upload_0Xo2DL-icon.png","medium":"https://s3.amazonaws.com/brewerydbapi/brewery/o4FfAx/upload_0Xo2DL-medium.png","large":"https://s3.amazonaws.com/brewerydbapi/brewery/o4FfAx/upload_0Xo2DL-large.png"}},"country":{"isoCode":"US","name":"UNITED STATES","displayName":"United States","isoThree":"USA","numberCode":840,"createDate":[2012,1,3,2,41,33]}}