{"breweryId":"n2527g","id":"Nrvt1a","name":"American Brown","abv":"5.9","isOrganic":"N","status":"verified","statusDisplay":"Verified","styleId":37,"glasswareId":5,"createDate":[2013,9,5,12,32,55],"updateDate":[2015,12,17,6,12,11],"labels":{"icon":"https://s3.amazonaws.com/brewerydbapi/beer/Nrvt1a/upload_IoLh64-icon.png","medium":"https://s3.amazonaws.com/brewerydbapi/beer/Nrvt1a/upload_IoLh64-medium.png","large":"https://s3.amazonaws.com/brewerydbapi/beer/Nrvt1a/upload_IoLh64-large.png"},"style":{"id":37,"categoryId":3,"name":"American-Style Brown Ale","shortName":"American Brown","description":"American brown ales range from deep copper to brown in color. Roasted malt caramel-like and chocolate-like characters should be of medium intensity in both flavor and aroma. American brown ales have evident low to medium hop flavor and aroma, medium to high hop bitterness, and a medium body. Estery and fruity-ester characters should be subdued. Diacetyl should not be perceived. Chill haze is allowable at cold temperatures.","ibuMin":"25","ibuMax":"45","abvMin":"4","abvMax":"6.4","srmMin":"15","srmMax":"26","ogMin":"1.04","fgMin":"1.01","fgMax":"1.018","createDate":[2012,3,21,20,6,46],"updateDate":[2015,4,7,15,27,35],"category":{"id":3,"name":"North American Origin Ales","createDate":[2012,3,21,20,6,45]}},"glass":{"id":5,"name":"Pint","createDate":[2012,1,3,2,41,33]}}